genranddata/README.MD
genranddata/__init__.py
genranddata/requirements.txt
genranddata/thirdparty.json
genranddata-0.10.dist-info/LICENSE.rst
genranddata-0.10.dist-info/METADATA
genranddata-0.10.dist-info/WHEEL
genranddata-0.10.dist-info/top_level.txt
genranddata-0.10.dist-info/RECORD
